pydeequ2/__init__.py
pydeequ2/analyzers.py
pydeequ2/anomaly_detection.py
pydeequ2/checks.py
pydeequ2/configs.py
pydeequ2/metrics.py
pydeequ2/pandas_utils.py
pydeequ2/profiles.py
pydeequ2/repository.py
pydeequ2/scala_utils.py
pydeequ2/suggestions.py
pydeequ2/verification.py
pydeequ2-1.0.2.dist-info/LICENSE
pydeequ2-1.0.2.dist-info/WHEEL
pydeequ2-1.0.2.dist-info/METADATA
pydeequ2-1.0.2.dist-info/RECORD
