Metadata-Version: 2.1
Name: pydeequ2
Version: 1.0.2
Summary: PyDeequ2 - aws clone
Home-page: https://pydeequ.readthedocs.io
License: Apache-2.0
Author: John Smith
Author-email: john@example.com
Maintainer: John Smith
Maintainer-email: john@example.com
Requires-Python: >=3.6.2,<4
Classifier: Development Status :: 4 - Beta
Classifier: License :: OSI Approved :: Apache Software License
Classifier: Programming Language :: Python :: 3
Classifier: Programming Language :: Python :: 3.7
Classifier: Programming Language :: Python :: 3.8
Classifier: Programming Language :: Python :: 3.9
Classifier: Programming Language :: Python :: 3.10
Classifier: Programming Language :: Python :: 3.11
Classifier: Programming Language :: Python :: 3
Provides-Extra: pyspark
Requires-Dist: numpy (>=1.14.1)
Requires-Dist: pandas (>=0.23.0)
Requires-Dist: pyspark (>=2.4.7,<3.3.0) ; extra == "pyspark"
Project-URL: Documentation, https://pydeequ.readthedocs.io
Project-URL: Repository, https://github.com/awslabs/python-deequ
